{
  "GUID": "5a02c3",
  "Name": "Card",
  "Transform": {
    "posX": 35.1449471,
    "posY": 1.65768564,
    "posZ": -3.912837,
    "rotX": -0.00132074382,
    "rotY": 179.999954,
    "rotZ": 182.475922,
    "scaleX": 1.35,
    "scaleY": 1.0,
    "scaleZ": 1.35
  },
  "Nickname": "",
  "Description": "",
  "GMNotes": "",
  "AltLookAngle": {
    "x": 0.0,
    "y": 0.0,
    "z": 0.0
  },
  "ColorDiffuse": {
    "r": 0.713235259,
    "g": 0.713235259,
    "b": 0.713235259
  },
  "LayoutGroupSortIndex": 0,
  "Value": 0,
  "Locked": false,
  "Grid": true,
  "Snap": true,
  "IgnoreFoW": false,
  "MeasureMovement": false,
  "DragSelectable": true,
  "Autoraise": true,
  "Sticky": true,
  "Tooltip": true,
  "GridProjection": false,
  "HideWhenFaceDown": true,
  "Hands": true,
  "CardID": 1900,
  "SidewaysCard": false,
  "CustomDeck": {
    "19": {
      "FaceURL": "https://steamusercontent-a.akamaihd.net/ugc/12795346229556005402/8EEBF369D8008240676BFFAC023BA8D0831F45AE/",
      "BackURL": "https://steamusercontent-a.akamaihd.net/ugc/14771864602372699774/67117EBE2071677442CC4CD30DDCA0D47D74B838/",
      "NumWidth": 6,
      "NumHeight": 5,
      "BackIsHidden": false,
      "UniqueBack": false,
      "Type": 0
    }
  }
}